xavi/common.py
xavi/setup.py
xavi-0.5.0.dist-info/METADATA
xavi-0.5.0.dist-info/WHEEL
xavi-0.5.0.dist-info/top_level.txt
xavi-0.5.0.dist-info/RECORD
