Metadata-Version: 2.1
Name: xavi
Version: 0.5.0
Summary: A collection of commonly used Python methods
Home-page: https://github.com/XavierWattermann/common
Author: Xavier Wattermann
Author-email: xwattermann@gmail.com
License: UNKNOWN
Download-URL: https://github.com/XavierWattermann/common/archive/0.5.tar.gz
Keywords: testing,debugging,common
Platform: UNKNOWN
